cachectl/__init__.py
cachectl/cli.py
cachectl-0.1.0.dist-info/METADATA
cachectl-0.1.0.dist-info/WHEEL
cachectl-0.1.0.dist-info/entry_points.txt
cachectl-0.1.0.dist-info/top_level.txt
cachectl-0.1.0.dist-info/RECORD
