Metadata-Version: 2.4
Name: cachectl
Version: 0.1.0
Summary: Configure cache directories for pnpm, npm, yarn, pip, poetry, and uv.
Requires-Python: >=3.10
Requires-Dist: build>=1.4.0
